real_useragent/__init__.py
real_useragent/agent.py
real_useragent/desktop_useragent.txt
real_useragent/get_agent.py
real_useragent/get_compile.py
real_useragent/mobile_useragent.txt
real_useragent-1.0.94.dist-info/METADATA
real_useragent-1.0.94.dist-info/WHEEL
real_useragent-1.0.94.dist-info/top_level.txt
real_useragent-1.0.94.dist-info/RECORD
