Metadata-Version: 2.4
Name: real_useragent
Version: 1.0.94
Summary: Get Real user agent from auto update
Home-page: https://github.com/useragenter/real-useragent
Author: Mohammadreza (MMDRZA)
Author-email: Pymmdrza@gmail.com
License: MIT
Project-URL: Bug Reports, https://github.com/useragenter/real-useragent/issues
Project-URL: Source, https://github.com/useragenter/real-useragent
Keywords: user-agent,useragenter,useragent,user agent,useragent,real user agent,real-useragent
Classifier: Programming Language :: Python :: 3
Classifier: License :: OSI Approved :: MIT License
Classifier: Operating System :: OS Independent
Dynamic: author
Dynamic: author-email
Dynamic: classifier
Dynamic: description
Dynamic: description-content-type
Dynamic: home-page
Dynamic: keywords
Dynamic: license
Dynamic: project-url
Dynamic: summary
